mindwidgets_df1201s.py
mindwidgets_circuitpython_df1201s-0.1.2.dist-info/LICENSE
mindwidgets_circuitpython_df1201s-0.1.2.dist-info/METADATA
mindwidgets_circuitpython_df1201s-0.1.2.dist-info/WHEEL
mindwidgets_circuitpython_df1201s-0.1.2.dist-info/top_level.txt
mindwidgets_circuitpython_df1201s-0.1.2.dist-info/RECORD
