Metadata-Version: 2.1
Name: mindwidgets-circuitpython-df1201s
Version: 0.1.2
Summary: CircuitPython driver for DFRobot DFPlayer Pro MP3 player with onboard storage
Author-email: Mindwidgets <aaron@mindwidgets.com>
License: MIT
Project-URL: Homepage, https://github.com/mindwidgets/Mindwidgets_CircuitPython_DF1201S
Keywords: adafruit,blinka,circuitpython,micropython,df1201s,dfplayer,mp3,wav,wma,flac,aac,ape,dfrobot
Classifier: Intended Audience :: Developers
Classifier: Topic :: Software Development :: Libraries
Classifier: Topic :: Software Development :: Embedded Systems
Classifier: Topic :: System :: Hardware
Classifier: License :: OSI Approved :: MIT License
Classifier: Programming Language :: Python :: 3
License-File: LICENSE
Requires-Dist: Adafruit-Blinka
Provides-Extra: optional
